{
  "friends": [
    { "word": "CENTRAL PERK", "hint": "Iconic coffee shop." },
    { "word": "SMELLY CAT", "hint": "Phoebe's unforgettable song." },
    { "word": "UNAGI", "hint": "Ross's 'state of total awareness'." },
    { "word": "REGINA PHALANGE", "hint": "Phoebe's fake name." },
    { "word": "HOW YOU DOIN", "hint": "Joey's famous catchphrase." }
  ],

  "science": [
    { "word": "GRAVITY", "hint": "Keeps your feet on the ground." },
    { "word": "PHOTOSYNTHESIS", "hint": "Plants love this process." },
    { "word": "BIG BANG", "hint": "One theory of how it all started." },
    { "word": "EVOLUTION", "hint": "Darwin wrote about it." },
    { "word": "BLACK HOLE", "hint": "Space-time with no escape." }
  ],

  "movies": [
    { "word": "JURASSIC PARK", "hint": "Dinosaurs on an island." },
    { "word": "INCEPTION", "hint": "We have to go deeper." },
    { "word": "THE MATRIX", "hint": "Blue pill or red pill?" },
    { "word": "HOGWARTS", "hint": "School of witchcraft and wizardry." },
    { "word": "LIGHTSABER", "hint": "Elegant weapon for a more civilized age." }
  ]
}
